unslothify/__init__.py
unslothify-0.0.1.dist-info/LICENSE
unslothify-0.0.1.dist-info/METADATA
unslothify-0.0.1.dist-info/WHEEL
unslothify-0.0.1.dist-info/top_level.txt
unslothify-0.0.1.dist-info/RECORD
